pycookie/__init__.py
pycookie/configs.py
pycookie/main.py
pycookie/static.py
pycookie-0.0.3.dist-info/LICENSE
pycookie-0.0.3.dist-info/METADATA
pycookie-0.0.3.dist-info/WHEEL
pycookie-0.0.3.dist-info/entry_points.txt
pycookie-0.0.3.dist-info/top_level.txt
pycookie-0.0.3.dist-info/RECORD
