Metadata-Version: 2.1
Name: pycookie
Version: 0.0.3
Summary: Pycookie will help you handle cookies
Home-page: https://veltzer.github.io/pycookie
Download-URL: https://github.com/veltzer/pycookie
Author: Mark Veltzer
Author-email: mark.veltzer@gmail.com
Maintainer: Mark Veltzer
Maintainer-email: mark.veltzer@gmail.com
License: MIT
Keywords: cookies,browser,chrome,firefox
Platform: python3
Classifier: Development Status :: 4 - Beta
Classifier: Environment :: Console
Classifier: Operating System :: OS Independent
Classifier: Programming Language :: Python
Classifier: Programming Language :: Python :: 3
Classifier: Programming Language :: Python :: 3 :: Only
Classifier: Programming Language :: Python :: 3.11
Classifier: Topic :: Utilities
Classifier: License :: OSI Approved :: MIT License
License-File: LICENSE
Requires-Dist: pytconf
Requires-Dist: pylogconf
Requires-Dist: browsercookie
